PATAT.cpython-38-darwin.so
PATAT_sim-0.1.data/scripts/runpatat.py
PATAT_sim-0.1.dist-info/LICENSE
PATAT_sim-0.1.dist-info/METADATA
PATAT_sim-0.1.dist-info/WHEEL
PATAT_sim-0.1.dist-info/top_level.txt
PATAT_sim-0.1.dist-info/RECORD
