Metadata-Version: 2.1
Name: PATAT-sim
Version: 0.1
Summary: A stochastic agent-based model to simulate SARS-CoV-2 epidemics.
Home-page: https://github.com/AMC-LAEB/PATAT-sim
Author: Alvin X Han, Brooke E Nichols, Colin A Russell
Author-email: x.han@amsterdamumc.nl
License: UNKNOWN
Platform: UNKNOWN
License-File: LICENSE
Requires-Dist: numpy (>=1.20.2)
Requires-Dist: scipy (>=1.6.2)
Requires-Dist: pandas (>=1.2.4)
Requires-Dist: openpyxl (>=3.0.7)
